neon_tts_plugin_coqui/__init__.py
neon_tts_plugin_coqui/configs.py
neon_tts_plugin_coqui-0.8.1.dist-info/LICENSE.md
neon_tts_plugin_coqui-0.8.1.dist-info/METADATA
neon_tts_plugin_coqui-0.8.1.dist-info/WHEEL
neon_tts_plugin_coqui-0.8.1.dist-info/entry_points.txt
neon_tts_plugin_coqui-0.8.1.dist-info/top_level.txt
neon_tts_plugin_coqui-0.8.1.dist-info/zip-safe
neon_tts_plugin_coqui-0.8.1.dist-info/RECORD
