Metadata-Version: 2.1
Name: neon-tts-plugin-coqui
Version: 0.8.1
Summary: A Coqui AI TTS plugin for Neon
Home-page: https://github.com/NeonGeckoCom/neon-tts-plugin-coqui
Author: Neongecko
Author-email: developers@neon.ai
License: BSD-3.0
Keywords: mycroft plugin tts
Classifier: Intended Audience :: Developers
Classifier: Topic :: Text Processing :: Linguistic
Classifier: Programming Language :: Python :: 3.6
License-File: LICENSE.md
Requires-Dist: numpy>=1.19.5
Requires-Dist: torch!=1.13.0,<2.4.0,>=1.9.0
Requires-Dist: ovos-plugin-manager>=0.0.23,~=0.0
Requires-Dist: ovos-utils>=0.0.32,~=0.0
Requires-Dist: psutil
Requires-Dist: huggingface-hub
Provides-Extra: docker
Requires-Dist: ovos-tts-server~=0.1; extra == "docker"
